odoo/addons/base_vat_sanitized/README.rst
odoo/addons/base_vat_sanitized/__init__.py
odoo/addons/base_vat_sanitized/__manifest__.py
odoo/addons/base_vat_sanitized/i18n/am.po
odoo/addons/base_vat_sanitized/i18n/ar.po
odoo/addons/base_vat_sanitized/i18n/bg.po
odoo/addons/base_vat_sanitized/i18n/bs.po
odoo/addons/base_vat_sanitized/i18n/ca.po
odoo/addons/base_vat_sanitized/i18n/cs.po
odoo/addons/base_vat_sanitized/i18n/da.po
odoo/addons/base_vat_sanitized/i18n/de.po
odoo/addons/base_vat_sanitized/i18n/el_GR.po
odoo/addons/base_vat_sanitized/i18n/en_GB.po
odoo/addons/base_vat_sanitized/i18n/es.po
odoo/addons/base_vat_sanitized/i18n/es_CR.po
odoo/addons/base_vat_sanitized/i18n/es_EC.po
odoo/addons/base_vat_sanitized/i18n/es_MX.po
odoo/addons/base_vat_sanitized/i18n/es_VE.po
odoo/addons/base_vat_sanitized/i18n/et.po
odoo/addons/base_vat_sanitized/i18n/eu.po
odoo/addons/base_vat_sanitized/i18n/fi.po
odoo/addons/base_vat_sanitized/i18n/fr.po
odoo/addons/base_vat_sanitized/i18n/fr_CA.po
odoo/addons/base_vat_sanitized/i18n/fr_CH.po
odoo/addons/base_vat_sanitized/i18n/gl.po
odoo/addons/base_vat_sanitized/i18n/hr.po
odoo/addons/base_vat_sanitized/i18n/hr_HR.po
odoo/addons/base_vat_sanitized/i18n/hu.po
odoo/addons/base_vat_sanitized/i18n/it.po
odoo/addons/base_vat_sanitized/i18n/ja.po
odoo/addons/base_vat_sanitized/i18n/lt.po
odoo/addons/base_vat_sanitized/i18n/lv.po
odoo/addons/base_vat_sanitized/i18n/mk.po
odoo/addons/base_vat_sanitized/i18n/mn.po
odoo/addons/base_vat_sanitized/i18n/nb.po
odoo/addons/base_vat_sanitized/i18n/nb_NO.po
odoo/addons/base_vat_sanitized/i18n/nl.po
odoo/addons/base_vat_sanitized/i18n/nl_BE.po
odoo/addons/base_vat_sanitized/i18n/nl_NL.po
odoo/addons/base_vat_sanitized/i18n/pl.po
odoo/addons/base_vat_sanitized/i18n/pt.po
odoo/addons/base_vat_sanitized/i18n/pt_BR.po
odoo/addons/base_vat_sanitized/i18n/pt_PT.po
odoo/addons/base_vat_sanitized/i18n/ro.po
odoo/addons/base_vat_sanitized/i18n/ru.po
odoo11_addon_base_vat_sanitized-11.0.1.0.0.dist-info/DESCRIPTION.rst
odoo11_addon_base_vat_sanitized-11.0.1.0.0.dist-info/METADATA
odoo11_addon_base_vat_sanitized-11.0.1.0.0.dist-info/RECORD
odoo11_addon_base_vat_sanitized-11.0.1.0.0.dist-info/WHEEL
odoo11_addon_base_vat_sanitized-11.0.1.0.0.dist-info/metadata.json
odoo11_addon_base_vat_sanitized-11.0.1.0.0.dist-info/top_level.txt
